afrigis_search_client/__init__.py
afrigis_search_client/auth.py
afrigis_search_client/endpoints.py
afrigis_search_client/request_authenticator.py
afrigis_search_client/token_manager.py
afrigis_search_client/autocomplete/__init__.py
afrigis_search_client/autocomplete/v3.py
afrigis_search_client/delivery/__init__.py
afrigis_search_client/delivery/v1.py
afrigis_search_client/details/__init__.py
afrigis_search_client/details/v3.py
afrigis_search_client/geocode/__init__.py
afrigis_search_client/geocode/v3.py
afrigis_search_client/models/autocomplete.py
afrigis_search_client/models/delivery.py
afrigis_search_client/models/details.py
afrigis_search_client/models/geocode.py
afrigis_search_client-0.1.1.dist-info/licenses/LICENSE
afrigis_search_client-0.1.1.dist-info/METADATA
afrigis_search_client-0.1.1.dist-info/WHEEL
afrigis_search_client-0.1.1.dist-info/top_level.txt
afrigis_search_client-0.1.1.dist-info/RECORD
