Metadata-Version: 2.4
Name: afrigis-search-client
Version: 0.1.1
Summary: A modern, async Python SDK for seamless integration with the AfriGIS Search suite of APIs. Provides robust, versioned, and strongly-typed access to Autocomplete, Geocode, Place Details, and Delivery Address Format endpoints, with automatic authentication and error handling.
Author-email: AfriGIS <products@afrigis.co.za>
License-Expression: MIT
Project-URL: Homepage, https://www.afrigis.co.za/
Project-URL: Repository, https://github.com/afrigis/afrigis-search-client
Classifier: Programming Language :: Python :: 3
Classifier: Operating System :: OS Independent
Requires-Python: >=3.7
License-File: LICENSE
Requires-Dist: aiohttp>=3.12.0
Requires-Dist: pydantic>=2.0.0
Requires-Dist: python-dotenv>=1.0.0
Dynamic: license-file
